datadog_mcp/__init__.py
datadog_mcp/server.py
datadog_mcp/tools/__init__.py
datadog_mcp/tools/aggregate_traces.py
datadog_mcp/tools/get_fingerprints.py
datadog_mcp/tools/get_logs.py
datadog_mcp/tools/get_logs_field_values.py
datadog_mcp/tools/get_metric_field_values.py
datadog_mcp/tools/get_metric_fields.py
datadog_mcp/tools/get_metrics.py
datadog_mcp/tools/get_service_definition.py
datadog_mcp/tools/get_teams.py
datadog_mcp/tools/get_traces.py
datadog_mcp/tools/list_metrics.py
datadog_mcp/tools/list_monitors.py
datadog_mcp/tools/list_pipelines.py
datadog_mcp/tools/list_service_definitions.py
datadog_mcp/tools/list_slos.py
datadog_mcp/utils/__init__.py
datadog_mcp/utils/datadog_client.py
datadog_mcp/utils/formatters.py
datadog_mcp-0.2.5.dist-info/METADATA
datadog_mcp-0.2.5.dist-info/WHEEL
datadog_mcp-0.2.5.dist-info/entry_points.txt
datadog_mcp-0.2.5.dist-info/RECORD
