Metadata-Version: 2.4
Name: datadog-mcp
Version: 0.2.5
Summary: Datadog MCP server
Requires-Python: >=3.13
Requires-Dist: datadog-api-client>=2.39.0
Requires-Dist: httpx>=0.28.1
Requires-Dist: mcp>=1.9.4
Provides-Extra: test
Requires-Dist: pytest-asyncio>=0.21.0; extra == 'test'
Requires-Dist: pytest-mock>=3.10.0; extra == 'test'
Requires-Dist: pytest>=7.0.0; extra == 'test'
